unicon/plugins/__init__.py
unicon/plugins/pid_tokens.csv
unicon/plugins/utils.py
unicon/plugins/aireos/__init__.py
unicon/plugins/aireos/connection_provider.py
unicon/plugins/aireos/patterns.py
unicon/plugins/aireos/service_implementation.py
unicon/plugins/aireos/service_statements.py
unicon/plugins/aireos/settings.py
unicon/plugins/aireos/statemachine.py
unicon/plugins/aireos/ap/__init__.py
unicon/plugins/aireos/ap/settings.py
unicon/plugins/aireos/ap/statemachine.py
unicon/plugins/apic/__init__.py
unicon/plugins/apic/connection.py
unicon/plugins/apic/patterns.py
unicon/plugins/apic/service_implementation.py
unicon/plugins/apic/service_patterns.py
unicon/plugins/apic/service_statements.py
unicon/plugins/apic/settings.py
unicon/plugins/apic/statemachine.py
unicon/plugins/asa/__init__.py
unicon/plugins/asa/patterns.py
unicon/plugins/asa/provider.py
unicon/plugins/asa/service_implementation.py
unicon/plugins/asa/settings.py
unicon/plugins/asa/statemachine.py
unicon/plugins/asa/statements.py
unicon/plugins/asa/ASAv/__init__.py
unicon/plugins/asa/ASAv/service_implementation.py
unicon/plugins/asa/ASAv/service_statements.py
unicon/plugins/asa/ASAv/settings.py
unicon/plugins/asa/ASAv/statemachine.py
unicon/plugins/asa/fp2k/__init__.py
unicon/plugins/asa/fp2k/patterns.py
unicon/plugins/asa/fp2k/service_implementation.py
unicon/plugins/asa/fp2k/settings.py
unicon/plugins/asa/fp2k/statemachine.py
unicon/plugins/asa/fp2k/statements.py
unicon/plugins/cheetah/__init__.py
unicon/plugins/cheetah/ap/__init__.py
unicon/plugins/cheetah/ap/patterns.py
unicon/plugins/cheetah/ap/service_implementation.py
unicon/plugins/cheetah/ap/service_patterns.py
unicon/plugins/cheetah/ap/service_statement.py
unicon/plugins/cheetah/ap/settings.py
unicon/plugins/cheetah/ap/statemachine.py
unicon/plugins/cimc/__init__.py
unicon/plugins/cimc/patterns.py
unicon/plugins/cimc/service_implementation.py
unicon/plugins/cimc/settings.py
unicon/plugins/cimc/statemachine.py
unicon/plugins/cimc/statements.py
unicon.plugins-25.9.dist-info/LICENSE
unicon.plugins-25.9.dist-info/METADATA
unicon.plugins-25.9.dist-info/WHEEL
unicon.plugins-25.9.dist-info/top_level.txt
unicon.plugins-25.9.dist-info/RECORD
